{
  "code": 0,
  "data": [
    {
      "goodsId": 1,
      "text": "测试描述12222",
      "imageUrl": "http://pic28.nipic.com/20130424/11588775_115415688157_2.jpg",
      "spanSize": 4
    },
    {
      "goodsId": 2,
      "text": "测试描述22222",
      "imageUrl": "http://pic33.nipic.com/20130907/12906030_161342990000_2.png",
      "spanSize": 2
    },
    {
      "goodsId": 3,
      "text": "测试描述3",
      "imageUrl": "http://img003.hc360.cn/m8/M06/2A/1A/wKhQpVYkPWeEbWn7AAAAAAHmpus944.jpg",
      "spanSize": 2
    },
    {
      "goodsId": 4,
      "imageUrl": "http://image2.homevv.com/files/product/big/20141110/13404600.jpg",
      "spanSize": 2
    },
    {
      "goodsId": 4,
      "imageUrl": "http://image4.homevv.com/files/product/big/20141113/13406160.jpg",
      "spanSize": 2
    },
    {
      "goodsId": 4,
      "imageUrl": "http://pic30.nipic.com/20130614/10412939_152442460377_2.jpg",
      "spanSize": 2
    },
    {
      "goodsId": 4,
      "imageUrl": "http://img.yougou.com/pics/adidas/2012/21006606/21006606_03_mb.jpg",
      "spanSize": 2
    },
    {
      "goodsId": 5,
      "text": "我是野广告",
      "spanSize": 4
    },
    {
      "goodsId": 5,
      "text": "测试描述5",
      "imageUrl": "http://img01.taopic.com/150126/318762-1501260U02880.jpg",
      "spanSize": 4
    },
    {
      "goodsId": 6,
      "text": "测试描述6",
      "imageUrl": "http://imgsrc.baidu.com/baike/pic/item/0b55b319ebc4b745a58395aecffc1e178a821576.jpg",
      "spanSize": 4
    },
    {
      "goodsId": 5,
      "text": "我又是野广告",
      "spanSize": 4
    }
  ]
}